LICENSE.txt
README.md
setup.cfg
setup.py
multi_agent_coordination/__init__.py
multi_agent_coordination/simulation.py
multi_agent_coordination.egg-info/PKG-INFO
multi_agent_coordination.egg-info/SOURCES.txt
multi_agent_coordination.egg-info/dependency_links.txt
multi_agent_coordination.egg-info/requires.txt
multi_agent_coordination.egg-info/top_level.txt