Metadata-Version: 2.1
Name: multi-agent-coordination
Version: 0.2
Summary: Identification of strategic choices under multi-agent systems, coordination game and social networks
Home-page: https://github.com/ankur-tutlani/multi-agent-coordination
Download-URL: https://github.com/ankur-tutlani/multi_agent_coordination/archive/refs/tags/v_02.tar.gz
Author: ankurtutlani
Author-email: ankur.tutlani@gmail.com
License: MIT
Keywords: game theory,evolutionary game,social norms,multi-agent systems,evolution,social network,computational economics,simulation,agent-based modeling,computation
Classifier: Development Status :: 3 - Alpha
Classifier: Intended Audience :: Developers
Classifier: Topic :: Software Development :: Build Tools
Classifier: License :: OSI Approved :: MIT License
Classifier: Programming Language :: Python :: 3.11
License-File: LICENSE.txt
